iploader/AbuseCheck.py
iploader/__init__.py
iploader/compare.py
iploader/database.py
iploader/file.py
iploader/readConfig.py
iploader-1.0.3.data/scripts/iploader
iploader-1.0.3.dist-info/LICENSE
iploader-1.0.3.dist-info/METADATA
iploader-1.0.3.dist-info/WHEEL
iploader-1.0.3.dist-info/top_level.txt
iploader-1.0.3.dist-info/RECORD
