Metadata-Version: 2.1
Name: iploader
Version: 1.0.3
Summary: AbuseIPDB Ip Checker
Home-page: https://github.com/Amiri83/IPloader
Author: Amir Amiri
Author-email: Amiri83@gmail.com
License: UNKNOWN
Platform: UNKNOWN
Classifier: Programming Language :: Python :: 3
Classifier: License :: OSI Approved :: MIT License
Classifier: Operating System :: OS Independent
Requires-Python: >=3.6
